{"frames": [

{
	"filename": "onion_jump0001.png",
	"frame": {"x":351,"y":1054,"w":123,"h":279},
	"rotated": false,
	"trimmed": false,
	"spriteSourceSize": {"x":0,"y":0,"w":123,"h":279},
	"sourceSize": {"w":123,"h":279}
},
{
	"filename": "onion_jump0002.png",
	"frame": {"x":726,"y":1054,"w":123,"h":279},
	"rotated": false,
	"trimmed": false,
	"spriteSourceSize": {"x":0,"y":0,"w":123,"h":279},
	"sourceSize": {"w":123,"h":279}
},
{
	"filename": "onion_jump0003.png",
	"frame": {"x":601,"y":1054,"w":123,"h":279},
	"rotated": false,
	"trimmed": false,
	"spriteSourceSize": {"x":0,"y":0,"w":123,"h":279},
	"sourceSize": {"w":123,"h":279}
},
{
	"filename": "onion_jump0004.png",
	"frame": {"x":851,"y":1054,"w":123,"h":279},
	"rotated": false,
	"trimmed": false,
	"spriteSourceSize": {"x":0,"y":0,"w":123,"h":279},
	"sourceSize": {"w":123,"h":279}
},
{
	"filename": "onion_jump0005.png",
	"frame": {"x":476,"y":1054,"w":123,"h":279},
	"rotated": false,
	"trimmed": false,
	"spriteSourceSize": {"x":0,"y":0,"w":123,"h":279},
	"sourceSize": {"w":123,"h":279}
},
{
	"filename": "onion_jump0006.png",
	"frame": {"x":226,"y":1054,"w":123,"h":279},
	"rotated": false,
	"trimmed": false,
	"spriteSourceSize": {"x":0,"y":0,"w":123,"h":279},
	"sourceSize": {"w":123,"h":279}
},
{
	"filename": "onion_jump0007.png",
	"frame": {"x":101,"y":1054,"w":123,"h":279},
	"rotated": false,
	"trimmed": false,
	"spriteSourceSize": {"x":0,"y":0,"w":123,"h":279},
	"sourceSize": {"w":123,"h":279}
},
{
	"filename": "onion_jump0008.png",
	"frame": {"x":2,"y":1335,"w":123,"h":279},
	"rotated": false,
	"trimmed": false,
	"spriteSourceSize": {"x":0,"y":0,"w":123,"h":279},
	"sourceSize": {"w":123,"h":279}
},
{
	"filename": "onion_jump0009.png",
	"frame": {"x":377,"y":1335,"w":123,"h":279},
	"rotated": false,
	"trimmed": false,
	"spriteSourceSize": {"x":0,"y":0,"w":123,"h":279},
	"sourceSize": {"w":123,"h":279}
},
{
	"filename": "onion_jump0010.png",
	"frame": {"x":752,"y":1335,"w":123,"h":279},
	"rotated": false,
	"trimmed": false,
	"spriteSourceSize": {"x":0,"y":0,"w":123,"h":279},
	"sourceSize": {"w":123,"h":279}
},
{
	"filename": "onion_jump0011.png",
	"frame": {"x":627,"y":1335,"w":123,"h":279},
	"rotated": false,
	"trimmed": false,
	"spriteSourceSize": {"x":0,"y":0,"w":123,"h":279},
	"sourceSize": {"w":123,"h":279}
},
{
	"filename": "onion_jump0012.png",
	"frame": {"x":877,"y":1335,"w":123,"h":279},
	"rotated": false,
	"trimmed": false,
	"spriteSourceSize": {"x":0,"y":0,"w":123,"h":279},
	"sourceSize": {"w":123,"h":279}
},
{
	"filename": "onion_jump0013.png",
	"frame": {"x":502,"y":1335,"w":123,"h":279},
	"rotated": false,
	"trimmed": false,
	"spriteSourceSize": {"x":0,"y":0,"w":123,"h":279},
	"sourceSize": {"w":123,"h":279}
},
{
	"filename": "onion_jump0014.png",
	"frame": {"x":252,"y":1335,"w":123,"h":279},
	"rotated": false,
	"trimmed": false,
	"spriteSourceSize": {"x":0,"y":0,"w":123,"h":279},
	"sourceSize": {"w":123,"h":279}
},
{
	"filename": "onion_jump0015.png",
	"frame": {"x":127,"y":1335,"w":123,"h":279},
	"rotated": false,
	"trimmed": false,
	"spriteSourceSize": {"x":0,"y":0,"w":123,"h":279},
	"sourceSize": {"w":123,"h":279}
},
{
	"filename": "onion_lose0001.png",
	"frame": {"x":404,"y":2,"w":132,"h":240},
	"rotated": false,
	"trimmed": false,
	"spriteSourceSize": {"x":0,"y":0,"w":132,"h":240},
	"sourceSize": {"w":132,"h":240}
},
{
	"filename": "onion_lose0002.png",
	"frame": {"x":538,"y":2,"w":132,"h":240},
	"rotated": false,
	"trimmed": false,
	"spriteSourceSize": {"x":0,"y":0,"w":132,"h":240},
	"sourceSize": {"w":132,"h":240}
},
{
	"filename": "onion_lose0003.png",
	"frame": {"x":270,"y":2,"w":132,"h":240},
	"rotated": false,
	"trimmed": false,
	"spriteSourceSize": {"x":0,"y":0,"w":132,"h":240},
	"sourceSize": {"w":132,"h":240}
},
{
	"filename": "onion_lose0004.png",
	"frame": {"x":2,"y":2,"w":132,"h":240},
	"rotated": false,
	"trimmed": false,
	"spriteSourceSize": {"x":0,"y":0,"w":132,"h":240},
	"sourceSize": {"w":132,"h":240}
},
{
	"filename": "onion_lose0005.png",
	"frame": {"x":136,"y":2,"w":132,"h":240},
	"rotated": false,
	"trimmed": false,
	"spriteSourceSize": {"x":0,"y":0,"w":132,"h":240},
	"sourceSize": {"w":132,"h":240}
},
{
	"filename": "onion_lose0006.png",
	"frame": {"x":672,"y":2,"w":132,"h":240},
	"rotated": false,
	"trimmed": false,
	"spriteSourceSize": {"x":0,"y":0,"w":132,"h":240},
	"sourceSize": {"w":132,"h":240}
},
{
	"filename": "onion_lose0007.png",
	"frame": {"x":270,"y":244,"w":132,"h":240},
	"rotated": false,
	"trimmed": false,
	"spriteSourceSize": {"x":0,"y":0,"w":132,"h":240},
	"sourceSize": {"w":132,"h":240}
},
{
	"filename": "onion_lose0008.png",
	"frame": {"x":136,"y":244,"w":132,"h":240},
	"rotated": false,
	"trimmed": false,
	"spriteSourceSize": {"x":0,"y":0,"w":132,"h":240},
	"sourceSize": {"w":132,"h":240}
},
{
	"filename": "onion_lose0009.png",
	"frame": {"x":806,"y":2,"w":132,"h":240},
	"rotated": false,
	"trimmed": false,
	"spriteSourceSize": {"x":0,"y":0,"w":132,"h":240},
	"sourceSize": {"w":132,"h":240}
},
{
	"filename": "onion_lose0010.png",
	"frame": {"x":2,"y":244,"w":132,"h":240},
	"rotated": false,
	"trimmed": false,
	"spriteSourceSize": {"x":0,"y":0,"w":132,"h":240},
	"sourceSize": {"w":132,"h":240}
},
{
	"filename": "onion_stand.png",
	"frame": {"x":2,"y":1054,"w":97,"h":275},
	"rotated": false,
	"trimmed": false,
	"spriteSourceSize": {"x":0,"y":0,"w":97,"h":275},
	"sourceSize": {"w":97,"h":275}
},
{
	"filename": "onion_win0001.png",
	"frame": {"x":870,"y":784,"w":122,"h":268},
	"rotated": false,
	"trimmed": false,
	"spriteSourceSize": {"x":0,"y":0,"w":122,"h":268},
	"sourceSize": {"w":122,"h":268}
},
{
	"filename": "onion_win0002.png",
	"frame": {"x":746,"y":784,"w":122,"h":268},
	"rotated": false,
	"trimmed": false,
	"spriteSourceSize": {"x":0,"y":0,"w":122,"h":268},
	"sourceSize": {"w":122,"h":268}
},
{
	"filename": "onion_win0003.png",
	"frame": {"x":126,"y":514,"w":122,"h":268},
	"rotated": false,
	"trimmed": false,
	"spriteSourceSize": {"x":0,"y":0,"w":122,"h":268},
	"sourceSize": {"w":122,"h":268}
},
{
	"filename": "onion_win0004.png",
	"frame": {"x":404,"y":244,"w":122,"h":268},
	"rotated": false,
	"trimmed": false,
	"spriteSourceSize": {"x":0,"y":0,"w":122,"h":268},
	"sourceSize": {"w":122,"h":268}
},
{
	"filename": "onion_win0005.png",
	"frame": {"x":652,"y":244,"w":122,"h":268},
	"rotated": false,
	"trimmed": false,
	"spriteSourceSize": {"x":0,"y":0,"w":122,"h":268},
	"sourceSize": {"w":122,"h":268}
},
{
	"filename": "onion_win0006.png",
	"frame": {"x":528,"y":244,"w":122,"h":268},
	"rotated": false,
	"trimmed": false,
	"spriteSourceSize": {"x":0,"y":0,"w":122,"h":268},
	"sourceSize": {"w":122,"h":268}
},
{
	"filename": "onion_win0007.png",
	"frame": {"x":776,"y":244,"w":122,"h":268},
	"rotated": false,
	"trimmed": false,
	"spriteSourceSize": {"x":0,"y":0,"w":122,"h":268},
	"sourceSize": {"w":122,"h":268}
},
{
	"filename": "onion_win0008.png",
	"frame": {"x":870,"y":514,"w":122,"h":268},
	"rotated": false,
	"trimmed": false,
	"spriteSourceSize": {"x":0,"y":0,"w":122,"h":268},
	"sourceSize": {"w":122,"h":268}
},
{
	"filename": "onion_win0009.png",
	"frame": {"x":126,"y":784,"w":122,"h":268},
	"rotated": false,
	"trimmed": false,
	"spriteSourceSize": {"x":0,"y":0,"w":122,"h":268},
	"sourceSize": {"w":122,"h":268}
},
{
	"filename": "onion_win0010.png",
	"frame": {"x":498,"y":784,"w":122,"h":268},
	"rotated": false,
	"trimmed": false,
	"spriteSourceSize": {"x":0,"y":0,"w":122,"h":268},
	"sourceSize": {"w":122,"h":268}
},
{
	"filename": "onion_win0011.png",
	"frame": {"x":250,"y":784,"w":122,"h":268},
	"rotated": false,
	"trimmed": false,
	"spriteSourceSize": {"x":0,"y":0,"w":122,"h":268},
	"sourceSize": {"w":122,"h":268}
},
{
	"filename": "onion_win0012.png",
	"frame": {"x":374,"y":784,"w":122,"h":268},
	"rotated": false,
	"trimmed": false,
	"spriteSourceSize": {"x":0,"y":0,"w":122,"h":268},
	"sourceSize": {"w":122,"h":268}
},
{
	"filename": "onion_win0013.png",
	"frame": {"x":2,"y":784,"w":122,"h":268},
	"rotated": false,
	"trimmed": false,
	"spriteSourceSize": {"x":0,"y":0,"w":122,"h":268},
	"sourceSize": {"w":122,"h":268}
},
{
	"filename": "onion_win0014.png",
	"frame": {"x":746,"y":514,"w":122,"h":268},
	"rotated": false,
	"trimmed": false,
	"spriteSourceSize": {"x":0,"y":0,"w":122,"h":268},
	"sourceSize": {"w":122,"h":268}
},
{
	"filename": "onion_win0015.png",
	"frame": {"x":2,"y":514,"w":122,"h":268},
	"rotated": false,
	"trimmed": false,
	"spriteSourceSize": {"x":0,"y":0,"w":122,"h":268},
	"sourceSize": {"w":122,"h":268}
},
{
	"filename": "onion_win0016.png",
	"frame": {"x":250,"y":514,"w":122,"h":268},
	"rotated": false,
	"trimmed": false,
	"spriteSourceSize": {"x":0,"y":0,"w":122,"h":268},
	"sourceSize": {"w":122,"h":268}
},
{
	"filename": "onion_win0017.png",
	"frame": {"x":622,"y":514,"w":122,"h":268},
	"rotated": false,
	"trimmed": false,
	"spriteSourceSize": {"x":0,"y":0,"w":122,"h":268},
	"sourceSize": {"w":122,"h":268}
},
{
	"filename": "onion_win0018.png",
	"frame": {"x":374,"y":514,"w":122,"h":268},
	"rotated": false,
	"trimmed": false,
	"spriteSourceSize": {"x":0,"y":0,"w":122,"h":268},
	"sourceSize": {"w":122,"h":268}
},
{
	"filename": "onion_win0019.png",
	"frame": {"x":498,"y":514,"w":122,"h":268},
	"rotated": false,
	"trimmed": false,
	"spriteSourceSize": {"x":0,"y":0,"w":122,"h":268},
	"sourceSize": {"w":122,"h":268}
},
{
	"filename": "onion_win0020.png",
	"frame": {"x":622,"y":784,"w":122,"h":268},
	"rotated": false,
	"trimmed": false,
	"spriteSourceSize": {"x":0,"y":0,"w":122,"h":268},
	"sourceSize": {"w":122,"h":268}
}],
"meta": {
	"app": "https://www.codeandweb.com/texturepacker",
	"version": "1.0",
	"image": "onion.png",
	"format": "RGBA8888",
	"size": {"w":1002,"h":1616},
	"scale": "1",
	"smartupdate": "$TexturePacker:SmartUpdate:cb0b578a29bfc6b5d21748fcea10d11d:37e99bc0384c075fd7bbc36857fc3d8b:17ef345b1560bb734747356d5432b504$"
}
}
