{"skeleton":{"hash":"HNPifJdOSMGXQN6jKrqFxki0/Ig","spine":"3.8.86","x":-74.71,"y":-0.43,"width":164.39,"height":226.37,"images":"./images/","audio":""},"bones":[{"name":"root","scaleX":0.5,"scaleY":0.5},{"name":"bumblebee","parent":"root","x":21.91,"y":209.67},{"name":"leg upper right","parent":"bumblebee","length":87.29,"rotation":-98.6,"x":-12.05,"y":-13.9},{"name":"leg lower right","parent":"leg upper right","length":101.33,"rotation":0.15,"x":76.3,"y":1.39},{"name":"skirt middle","parent":"bumblebee","length":51.35,"rotation":-91.73,"x":-1.63,"y":1.78},{"name":"body","parent":"bumblebee","length":63,"rotation":90,"x":-0.97,"y":-0.1},{"name":"arm upper right","parent":"body","length":47.37,"rotation":162.86,"x":60.99,"y":24.32},{"name":"arm lower right","parent":"arm upper right","length":57.93,"rotation":0.14,"x":49.98,"y":-4.8},{"name":"hand right","parent":"arm lower right","length":23.95,"rotation":-16.94,"x":68.8,"y":5.7},{"name":"arm upper left","parent":"body","length":47.37,"rotation":-165.09,"x":61.28,"y":-18.02,"scaleY":-1},{"name":"arm lower left","parent":"arm upper left","length":57.93,"rotation":-5.76,"x":47.59,"y":-2.69},{"name":"hand left","parent":"arm lower left","length":23.95,"rotation":-16.27,"x":68.79,"y":5.12},{"name":"head","parent":"body","length":54.09,"rotation":-2.64,"x":84.23,"y":0.91},{"name":"pupil","parent":"head","rotation":-88.38,"x":38.06,"y":13.66},{"name":"pupil2","parent":"head","rotation":-88.38,"x":39.76,"y":-25.23},{"name":"eyebrow right","parent":"head","x":59.85,"y":14.28},{"name":"eyebrow left","parent":"head","rotation":0.86,"x":61.72,"y":-29.58,"scaleY":-1},{"name":"foot right","parent":"leg lower right","length":39.04,"rotation":98.11,"x":119.16,"y":1.78},{"name":"leg upper left","parent":"bumblebee","length":87.29,"rotation":-86.17,"x":11.68,"y":-13.9},{"name":"leg lower right2","parent":"leg upper left","length":101.33,"rotation":-12.19,"x":75.92,"y":1.33},{"name":"foot right2","parent":"leg lower right2","length":39.04,"rotation":98.66,"x":119.04,"y":1.75},{"name":"antena right","parent":"head","length":86.33,"rotation":24,"x":51.08,"y":-11.55},{"name":"antena left","parent":"head","length":86.33,"rotation":-9.63,"x":51.12,"y":-12.34,"scaleY":-1},{"name":"wing upper right","parent":"body","length":134.12,"rotation":54.13,"x":30.45,"y":5.82},{"name":"wing lower right","parent":"body","length":79.6,"rotation":126.37,"x":30.45,"y":4.59},{"name":"wing upper right2","parent":"body","length":134.12,"rotation":130.91,"x":30.45,"y":5.82,"scaleX":-1},{"name":"wing lower right2","parent":"body","length":79.6,"rotation":59.75,"x":30.45,"y":4.59,"scaleX":-1}],"slots":[{"name":"Bumblebee/wing upper","bone":"wing upper right","attachment":"bumblebee/wing upper"},{"name":"Bumblebee/wing upper2","bone":"wing upper right2","attachment":"bumblebee/wing upper"},{"name":"Bumblebee/wing lower","bone":"wing lower right","attachment":"bumblebee/wing lower"},{"name":"Bumblebee/wing lower2","bone":"wing lower right2","attachment":"bumblebee/wing lower"},{"name":"hand right open2","bone":"hand left","attachment":"bumblebee/hand fist"},{"name":"arm upper left","bone":"arm upper left","attachment":"bumblebee/arm upper"},{"name":"arm lower2","bone":"arm lower left","attachment":"bumblebee/arm lower"},{"name":"foot2","bone":"foot right2","attachment":"bumblebee/foot"},{"name":"leg upper2","bone":"leg upper left","attachment":"bumblebee/leg upper"},{"name":"leg lower2","bone":"leg lower right2","attachment":"bumblebee/leg lower"},{"name":"foot","bone":"foot right","attachment":"bumblebee/foot"},{"name":"leg upper","bone":"leg upper right","attachment":"bumblebee/leg upper"},{"name":"leg lower","bone":"leg lower right","attachment":"bumblebee/leg lower"},{"name":"torso","bone":"body","attachment":"bumblebee/torso"},{"name":"skirt middle","bone":"skirt middle","attachment":"bumblebee/hip"},{"name":"eye white","bone":"head","attachment":"bumblebee/eye white"},{"name":"pupil","bone":"pupil","attachment":"bumblebee/pupil"},{"name":"pupil2","bone":"pupil2","attachment":"bumblebee/pupil"},{"name":"head","bone":"head","attachment":"bumblebee/head"},{"name":"mouth_up","bone":"head","attachment":"bumblebee/mouth up open"},{"name":"eyebrow right","bone":"eyebrow right","attachment":"bumblebee/eyebrow"},{"name":"eyebrow left","bone":"eyebrow left","attachment":"bumblebee/eyebrow"},{"name":"Bumblebee/eyes","bone":"head","attachment":"bumblebee/eyes"},{"name":"Bumblebee/helmet","bone":"head","attachment":"bumblebee/helmet"},{"name":"Bumblebee/antena","bone":"antena right","attachment":"bumblebee/antena"},{"name":"Bumblebee/antena2","bone":"antena left","attachment":"bumblebee/antena"},{"name":"arm upper right","bone":"arm upper right","attachment":"bumblebee/arm upper"},{"name":"hand right open","bone":"hand right","attachment":"bumblebee/hand fist"},{"name":"arm lower right","bone":"arm lower right","attachment":"bumblebee/arm lower"}],"skins":[{"name":"default","attachments":{"Bumblebee/antena":{"bumblebee/antena":{"x":53.61,"y":-3.87,"rotation":-108.48,"width":31,"height":106}},"Bumblebee/antena2":{"bumblebee/antena":{"x":53.61,"y":-3.87,"rotation":-108.48,"width":31,"height":106}},"Bumblebee/eyes":{"bumblebee/eyes":{"x":38.1,"y":-5.12,"rotation":-87.36,"width":89,"height":33},"bumblebee/eyes blink":{"x":38.1,"y":-5.12,"rotation":-87.36,"width":89,"height":35}},"Bumblebee/helmet":{"bumblebee/helmet":{"x":49.09,"y":5.54,"rotation":-87.36,"width":116,"height":106}},"Bumblebee/wing lower":{"bumblebee/wing lower":{"x":72.15,"y":-7.15,"rotation":145.38,"width":130,"height":83}},"Bumblebee/wing lower2":{"bumblebee/wing lower":{"x":72.15,"y":-7.15,"rotation":145.38,"width":130,"height":83}},"Bumblebee/wing upper":{"bumblebee/wing upper":{"x":106.16,"y":-8.52,"rotation":-144.13,"width":167,"height":146}},"Bumblebee/wing upper2":{"bumblebee/wing upper":{"x":106.16,"y":-8.52,"rotation":-144.13,"width":167,"height":146}},"arm lower right":{"bumblebee/arm lower":{"x":29.61,"y":2.33,"rotation":102.48,"width":38,"height":87}},"arm lower2":{"bumblebee/arm lower":{"x":29.7,"y":-0.57,"rotation":96.88,"width":38,"height":87}},"arm upper left":{"bumblebee/arm upper":{"x":24.21,"y":-0.41,"rotation":92.96,"width":16,"height":56}},"arm upper right":{"bumblebee/arm upper":{"x":24.33,"y":-0.37,"rotation":92.88,"width":16,"height":56}},"eye white":{"bumblebee/eye white":{"x":38.18,"y":-4.33,"rotation":-88.38,"width":73,"height":38}},"eyebrow left":{"bumblebee/eyebrow":{"x":-3.79,"y":-1.42,"rotation":-90.52,"width":29,"height":11}},"eyebrow right":{"bumblebee/eyebrow":{"x":-3.44,"y":-0.85,"rotation":-87.36,"width":29,"height":11}},"foot":{"bumblebee/foot":{"x":25.82,"y":13.02,"rotation":0.42,"width":57,"height":31}},"foot2":{"bumblebee/foot":{"x":25.95,"y":12.66,"rotation":-0.13,"width":57,"height":31}},"hand right open":{"bumblebee/hand fist":{"x":10.29,"y":-0.21,"rotation":126.21,"width":23,"height":20},"bumblebee/hand open":{"x":12.78,"y":-8.75,"rotation":115.79,"width":33,"height":19}},"hand right open2":{"bumblebee/hand fist":{"x":11.03,"y":-0.79,"rotation":125.33,"width":23,"height":20},"bumblebee/hand open":{"x":16.63,"y":-3.17,"rotation":134.67,"width":33,"height":19}},"head":{"bumblebee/head":{"x":42.92,"y":4.62,"rotation":-88.38,"width":95,"height":97}},"leg lower":{"bumblebee/leg lower":{"x":56.62,"y":2.41,"rotation":98.09,"width":41,"height":129}},"leg lower2":{"bumblebee/leg lower":{"x":56.62,"y":2.41,"rotation":98.09,"width":41,"height":129}},"leg upper":{"bumblebee/leg upper":{"x":37.24,"y":-1.47,"rotation":98.39,"width":26,"height":91}},"leg upper2":{"bumblebee/leg upper":{"x":36.77,"y":0.26,"rotation":95.76,"width":26,"height":91}},"mouth_up":{"bumblebee/mouth down":{"x":12.83,"y":-12.78,"rotation":-88.38,"width":22,"height":12},"bumblebee/mouth down teeth":{"x":12.83,"y":-12.78,"rotation":-88.38,"width":21,"height":16},"bumblebee/mouth oo":{"x":12.83,"y":-12.78,"rotation":-88.38,"width":13,"height":16},"bumblebee/mouth up":{"x":14.16,"y":-13.75,"rotation":-88.38,"width":27,"height":14},"bumblebee/mouth up open":{"x":12.21,"y":-13.51,"rotation":-85.32,"width":28,"height":24}},"pupil":{"bumblebee/pupil":{"width":20,"height":20}},"pupil2":{"bumblebee/pupil":{"width":20,"height":20}},"skirt middle":{"bumblebee/hip":{"x":14.57,"y":-1.83,"rotation":90,"width":67,"height":35}},"torso":{"bumblebee/torso":{"x":35.1,"y":3.01,"rotation":-90,"width":60,"height":115}}}}],"events":{"OnFootstep":{},"OnSwim":{},"hit":{},"play_sound":{"string":"weight_drop"},"throw":{}},"animations":{"lose":{"slots":{"hand right open":{"attachment":[{"name":"bumblebee/hand open"}]},"hand right open2":{"attachment":[{"name":"bumblebee/hand open"}]},"mouth_up":{"attachment":[{"name":"bumblebee/mouth down"}]}},"bones":{"antena right":{"rotate":[{},{"time":0.3333,"angle":4.1},{"time":0.8333,"angle":0.6},{"time":1.2667,"angle":-10.34},{"time":1.4,"angle":-13.98},{"time":2}]},"antena left":{"rotate":[{},{"time":0.3333,"angle":4.21},{"time":0.8333,"angle":0.7},{"time":1.2667,"angle":-9.69},{"time":1.4,"angle":-13.15},{"time":2}]},"head":{"rotate":[{"angle":-4.27,"curve":0.25,"c3":0.625,"c4":0.5},{"time":0.1667,"angle":-2.37,"curve":0.25,"c3":0.625,"c4":0.5},{"time":1.2667,"angle":-12.17,"curve":0.375,"c2":0.5,"c3":0.75},{"time":2,"angle":-4.27}],"translate":[{"time":0.1667},{"time":1.2667,"x":-2.48,"y":-0.88},{"time":2}]},"wing lower right":{"rotate":[{"angle":20.95},{"time":0.2,"angle":-28.39},{"time":0.3,"angle":20.95},{"time":0.5,"angle":-28.39},{"time":0.6,"angle":20.95},{"time":0.8,"angle":-28.39},{"time":0.9,"angle":20.95},{"time":1.1,"angle":-28.39},{"time":1.2,"angle":20.95},{"time":1.4,"angle":-28.39},{"time":1.5,"angle":20.95},{"time":1.7,"angle":-28.39},{"time":1.8,"angle":20.95},{"time":1.9,"angle":-28.39},{"time":2,"angle":20.95}]},"wing lower right2":{"rotate":[{"angle":-24.19},{"time":0.2,"angle":21.27},{"time":0.3,"angle":-24.19},{"time":0.5,"angle":21.27},{"time":0.6,"angle":-24.19},{"time":0.8,"angle":21.27},{"time":0.9,"angle":-24.19},{"time":1.1,"angle":21.27},{"time":1.2,"angle":-24.19},{"time":1.4,"angle":21.27},{"time":1.5,"angle":-24.19},{"time":1.7,"angle":21.27},{"time":1.8,"angle":-24.19},{"time":1.9,"angle":21.27},{"time":2,"angle":-24.19}]},"wing upper right":{"rotate":[{"angle":22.97},{"time":0.1667,"angle":-19.81},{"time":0.3,"angle":22.99},{"time":0.4667,"angle":-19.81},{"time":0.6,"angle":22.99},{"time":0.7667,"angle":-19.81},{"time":0.9,"angle":22.99},{"time":1.0667,"angle":-19.81},{"time":1.2,"angle":22.99},{"time":1.3667,"angle":-19.81},{"time":1.5,"angle":22.99},{"time":1.6667,"angle":-19.81},{"time":1.8,"angle":22.99},{"time":1.9,"angle":-19.81},{"time":2,"angle":22.99}]},"wing upper right2":{"rotate":[{"angle":-22.83},{"time":0.1667,"angle":7.31},{"time":0.3,"angle":-22.83},{"time":0.4667,"angle":7.31},{"time":0.6,"angle":-22.83},{"time":0.7667,"angle":7.31},{"time":0.9,"angle":-22.83},{"time":1.0667,"angle":7.31},{"time":1.2,"angle":-22.83},{"time":1.3667,"angle":7.31},{"time":1.5,"angle":-22.83},{"time":1.6667,"angle":7.31},{"time":1.8,"angle":-22.83},{"time":1.9,"angle":7.31},{"time":2,"angle":-22.83}]},"arm lower left":{"rotate":[{"angle":-5.43,"curve":"stepped"},{"time":0.1667,"angle":-5.43},{"time":1.1667,"angle":-12.03},{"time":2,"angle":-5.43}]},"arm lower right":{"rotate":[{"angle":-2.26,"curve":"stepped"},{"time":0.1667,"angle":-2.26},{"time":1.1667,"angle":7.34},{"time":2,"angle":-2.26}]},"arm upper left":{"rotate":[{"angle":1.1,"curve":"stepped"},{"time":0.1667,"angle":1.1},{"time":1.1667,"angle":-7.55},{"time":2,"angle":1.1}]},"arm upper right":{"rotate":[{"angle":18.77,"curve":"stepped"},{"time":0.1667,"angle":18.77},{"time":1.1667,"angle":10.17},{"time":2,"angle":18.77}]},"eyebrow left":{"rotate":[{"angle":143.81,"curve":"stepped"},{"time":2}]},"eyebrow right":{"rotate":[{"angle":-149.56,"curve":"stepped"},{"time":2}]},"foot right":{"rotate":[{"angle":-28.51}]},"foot right2":{"rotate":[{"angle":-31.65}]},"hand right":{"rotate":[{"angle":61.67,"curve":"stepped"},{"time":2,"angle":44.2}]},"hand left":{"rotate":[{"angle":25.18}]},"leg lower right":{"rotate":[{"angle":-12.05}]},"leg lower right2":{"rotate":[{"angle":-48.59,"curve":0.25,"c3":0.625,"c4":0.5},{"time":1,"angle":-40.46,"curve":0.375,"c2":0.5,"c3":0.75},{"time":2,"angle":-48.59}]},"leg upper right":{"rotate":[{"angle":0.7,"curve":0.25,"c3":0.75},{"time":1,"angle":4.8,"curve":0.25,"c3":0.75},{"time":2,"angle":0.7}]},"leg upper left":{"rotate":[{"angle":4.47,"curve":0.25,"c3":0.75},{"time":1.1667,"angle":8.56,"curve":0.25,"c3":0.75},{"time":2,"angle":4.47}]},"pupil":{"translate":[{"x":-8.34,"y":-8.54}]},"pupil2":{"translate":[{"x":-8.72,"y":-2.58}]},"body":{"rotate":[{"angle":-17.73},{"time":1,"angle":-19.6},{"time":2,"angle":-17.73}]},"root":{"translate":[{"curve":0.48,"c3":0.599},{"time":1,"y":3.88,"curve":0.48,"c3":0.599},{"time":2}],"scale":[{"x":0.7,"y":0.7}]},"bumblebee":{"translate":[{"x":-21.91,"y":-209.67}]}}},"win":{"slots":{"hand right open":{"attachment":[{"name":"bumblebee/hand open"}]},"hand right open2":{"attachment":[{"name":"bumblebee/hand open"}]}},"bones":{"antena right":{"rotate":[{},{"time":0.6667,"angle":-2.89},{"time":1.3333}]},"antena left":{"rotate":[{},{"time":0.6667,"angle":-1.65},{"time":1.3333}]},"head":{"rotate":[{"curve":0.25,"c3":0.75},{"time":0.1667,"angle":-7.43,"curve":0.25,"c3":0.75},{"time":0.8333,"angle":13.82,"curve":0.25,"c3":0.75},{"time":1.3333}]},"wing lower right":{"rotate":[{"angle":20.95},{"time":0.1333,"angle":-28.39},{"time":0.2,"angle":20.95},{"time":0.3333,"angle":-28.39},{"time":0.4,"angle":20.95},{"time":0.5333,"angle":-28.39},{"time":0.6,"angle":20.95},{"time":0.7333,"angle":-28.39},{"time":0.8,"angle":20.95},{"time":0.9333,"angle":-28.39},{"time":1,"angle":20.95},{"time":1.1333,"angle":-28.39},{"time":1.2,"angle":20.95},{"time":1.2667,"angle":-28.39},{"time":1.3333,"angle":20.95}]},"wing lower right2":{"rotate":[{"angle":-24.19},{"time":0.1333,"angle":21.27},{"time":0.2,"angle":-24.19},{"time":0.3333,"angle":21.27},{"time":0.4,"angle":-24.19},{"time":0.5333,"angle":21.27},{"time":0.6,"angle":-24.19},{"time":0.7333,"angle":21.27},{"time":0.8,"angle":-24.19},{"time":0.9333,"angle":21.27},{"time":1,"angle":-24.19},{"time":1.1333,"angle":21.27},{"time":1.2,"angle":-24.19},{"time":1.2667,"angle":21.27},{"time":1.3333,"angle":-24.19}]},"wing upper right":{"rotate":[{"angle":22.99},{"time":0.1,"angle":-19.81},{"time":0.2,"angle":22.99},{"time":0.3,"angle":-19.81},{"time":0.4,"angle":22.99},{"time":0.5,"angle":-19.81},{"time":0.6,"angle":22.99},{"time":0.7,"angle":-19.81},{"time":0.8,"angle":22.99},{"time":0.9,"angle":-19.81},{"time":1,"angle":22.99},{"time":1.1,"angle":-19.81},{"time":1.2,"angle":22.99},{"time":1.3333,"angle":-19.81}]},"wing upper right2":{"rotate":[{"angle":-22.83},{"time":0.1,"angle":7.31},{"time":0.2,"angle":-22.83},{"time":0.3,"angle":7.31},{"time":0.4,"angle":-22.83},{"time":0.5,"angle":7.31},{"time":0.6,"angle":-22.83},{"time":0.7,"angle":7.31},{"time":0.8,"angle":-22.83},{"time":0.9,"angle":7.31},{"time":1,"angle":-22.83},{"time":1.1,"angle":7.31},{"time":1.2,"angle":-22.83},{"time":1.3333,"angle":7.31}]},"arm lower left":{"rotate":[{"angle":-120.16},{"time":0.3333,"angle":-40.69},{"time":0.6667,"angle":-120.16},{"time":1,"angle":-40.69},{"time":1.3333,"angle":-120.16}]},"arm lower right":{"rotate":[{"angle":-112.91},{"time":0.3333,"angle":-34.67},{"time":0.6667,"angle":-112.91},{"time":1,"angle":-34.67},{"time":1.3333,"angle":-112.91}]},"arm upper left":{"rotate":[{"angle":-7.55},{"time":0.3333,"angle":85.37},{"time":0.6667,"angle":-7.55},{"time":1,"angle":85.37},{"time":1.3333,"angle":-7.55}]},"arm upper right":{"rotate":[{},{"time":0.3333,"angle":-91.96},{"time":0.6667},{"time":1,"angle":-91.96},{"time":1.3333}]},"foot right":{"rotate":[{"angle":-28.51}]},"foot right2":{"rotate":[{"angle":-31.65}]},"hand right":{"rotate":[{"angle":7.28}],"scale":[{"y":-1}]},"hand left":{"rotate":[{"angle":6.4}],"scale":[{"y":-1}]},"leg lower right":{"rotate":[{"angle":-71.56,"curve":"stepped"},{"time":0.1667,"angle":-71.56,"curve":0.25,"c3":0.75},{"time":0.8333,"angle":-52.31,"curve":0.369,"c2":0.63,"c3":0.706},{"time":1.3333,"angle":-71.56}]},"leg lower right2":{"rotate":[{"angle":-43.96,"curve":0.25,"c3":0.75},{"time":0.7333,"angle":-15.3,"curve":0.25,"c3":0.75},{"time":1.3333,"angle":-43.96}]},"leg upper right":{"rotate":[{"angle":11.62,"curve":0.25,"c3":0.75},{"time":0.6667,"angle":14.62,"curve":0.25,"c3":0.75},{"time":1.3333,"angle":11.62}]},"leg upper left":{"rotate":[{"angle":5.02,"curve":0.25,"c3":0.75},{"time":0.6667,"angle":13.91,"curve":0.25,"c3":0.75},{"time":1.3333,"angle":5.02}]},"skirt middle":{"rotate":[{},{"time":0.6667,"angle":11.32},{"time":1.3333}]},"body":{"rotate":[{},{"time":0.1,"angle":-1.69},{"time":0.7667,"angle":16.3},{"time":1.3333}]},"root":{"translate":[{"curve":0.48,"c3":0.599},{"time":0.6667,"y":3.88,"curve":0.48,"c3":0.599},{"time":1.3333}],"scale":[{"x":0.7,"y":0.7}]},"bumblebee":{"translate":[{"x":-21.91,"y":-209.67}]}}}}}